wg_client_work/__init__.py
wg_client_work/client.py
wg_client_work/driver_factory.py
wg_client_work/exceptions.py
wg_client_work-0.1.dist-info/licenses/LICENSE
wg_client_work-0.1.dist-info/METADATA
wg_client_work-0.1.dist-info/WHEEL
wg_client_work-0.1.dist-info/top_level.txt
wg_client_work-0.1.dist-info/RECORD
