Metadata-Version: 2.4
Name: wg_client_work
Version: 0.1
License-File: LICENSE
Requires-Dist: selenium
Requires-Dist: webdriver-manager
Dynamic: license-file
Dynamic: requires-dist
